{
  "id": "prophet",
  "name": "先知",
  "godType": "intelligence",
  "description": "洞悉的命运之眼",
  "tags": [
    "冰冷"
  ],
  "totalPoints": 35,
  "allocatedPoints": 0,
  "coreRequiredPoints": 24,
  "coreTalents": [
    {
      "id": "core_0",
      "name": "冻伤",
      "type": "legendary",
      "description": "造成击中冰冷伤害时，施加冰结\n+50% 冰结效果 （神格生效上限：1）",
      "effects": [
        "造成击中冰冷伤害时，施加冰结",
        "+50% 冰结效果 （神格生效上限：1）"
      ],
      "requiredPoints": 24,
      "maxPoints": 1,
      "currentPoints": 0,
      "position": {
        "row": 0,
        "col": 0,
        "x": 150,
        "y": 30
      },
      "connections": [],
      "icon": "/assets/talents/UI/Textures/Common/Icon/Skill/CoreTalentIcon/128/UI_CoreTalentIcon_dongshang_Icon_128.webp"
    },
    {
      "id": "core_1",
      "name": "刺骨极寒",
      "type": "legendary",
      "description": "+50 冰结值上限\n你只能造成冰冷伤害 （神格生效上限：1）",
      "effects": [
        "+50 冰结值上限",
        "你只能造成冰冷伤害 （神格生效上限：1）"
      ],
      "requiredPoints": 24,
      "maxPoints": 1,
      "currentPoints": 0,
      "position": {
        "row": 0,
        "col": 1,
        "x": 350,
        "y": 30
      },
      "connections": [],
      "icon": "/assets/talents/UI/Textures/Common/Icon/Skill/CoreTalentIcon/128/UI_CoreTalentIcon_bingdian_Icon_128.webp"
    },
    {
      "id": "core_2",
      "name": "心灵利刃",
      "type": "legendary",
      "description": "未携带法杖、锡杖时，附加 30% 物理伤害的冰冷伤害\n携带法杖或锡杖时，额外 +25% 冰冷伤害 （神格生效上限：1）",
      "effects": [
        "未携带法杖、锡杖时，附加 30% 物理伤害的冰冷伤害",
        "携带法杖或锡杖时，额外 +25% 冰冷伤害 （神格生效上限：1）"
      ],
      "requiredPoints": 24,
      "maxPoints": 1,
      "currentPoints": 0,
      "position": {
        "row": 0,
        "col": 2,
        "x": 550,
        "y": 30
      },
      "connections": [],
      "icon": "/assets/talents/UI/Textures/Common/Icon/Skill/CoreTalentIcon/128/UI_CoreTalentIcon_xinlingliren_Icon_128.webp"
    },
    {
      "id": "core_3",
      "name": "冰冻之莲",
      "type": "legendary",
      "description": "额外 +25% 冰冷伤害\n额外 +25% 召唤物冰冷伤害\n技能不消耗魔力 （神格生效上限：1）",
      "effects": [
        "额外 +25% 冰冷伤害",
        "额外 +25% 召唤物冰冷伤害",
        "技能不消耗魔力 （神格生效上限：1）"
      ],
      "requiredPoints": 24,
      "maxPoints": 1,
      "currentPoints": 0,
      "position": {
        "row": 0,
        "col": 3,
        "x": 750,
        "y": 30
      },
      "connections": [],
      "icon": "/assets/talents/UI/Textures/Common/Icon/Skill/CoreTalentIcon/128/UI_CoreTalentIcon_bingdongzhilian_Icon_128.webp"
    }
  ],
  "nodes": [
    {
      "id": "node_0",
      "name": "+9% 冰冷伤害",
      "type": "small",
      "effects": [
        "+9% 冰冷伤害"
      ],
      "requiredPoints": 0,
      "maxPoints": 3,
      "currentPoints": 0,
      "position": {
        "row": 1,
        "col": 0,
        "x": 96.0,
        "y": 80.0
      },
      "connections": [
        "node_1"
      ],
      "icon": "/assets/talents/UI/Textures/Common/Icon/Silhouette/Talent/64/Claw02_64.webp"
    },
    {
      "id": "node_13",
      "name": "+3% 最大生命",
      "type": "small",
      "effects": [
        "+3% 最大生命",
        "+3% 最大护盾"
      ],
      "requiredPoints": 0,
      "maxPoints": 3,
      "currentPoints": 0,
      "position": {
        "row": 3,
        "col": 0,
        "x": 96.0,
        "y": 272.0
      },
      "connections": [
        "node_14"
      ],
      "icon": "/assets/talents/UI/Textures/Common/Icon/Silhouette/Talent/64/Aura_64.webp"
    },
    {
      "id": "node_25",
      "name": "+9% 冰冷伤害",
      "type": "small",
      "effects": [
        "+9% 冰冷伤害",
        "召唤物 +9% 冰冷伤害"
      ],
      "requiredPoints": 0,
      "maxPoints": 3,
      "currentPoints": 0,
      "position": {
        "row": 5,
        "col": 0,
        "x": 96.0,
        "y": 464.0
      },
      "connections": [
        "node_26"
      ],
      "icon": "/assets/talents/UI/Textures/Common/Icon/Silhouette/Talent/64/DmgCold_64.webp"
    },
    {
      "id": "node_1",
      "name": "+18% 冰冷伤害",
      "type": "notable",
      "effects": [
        "+18% 冰冷伤害"
      ],
      "requiredPoints": 3,
      "maxPoints": 3,
      "currentPoints": 0,
      "position": {
        "row": 1,
        "col": 1,
        "x": 224.0,
        "y": 80.0
      },
      "connections": [
        "node_0"
      ],
      "icon": "/assets/talents/UI/Textures/Common/Icon/Silhouette/Talent/64/Claw02_64.webp"
    },
    {
      "id": "node_14",
      "name": "+6% 最大生命",
      "type": "notable",
      "effects": [
        "+6% 最大生命",
        "+6% 最大护盾"
      ],
      "requiredPoints": 3,
      "maxPoints": 3,
      "currentPoints": 0,
      "position": {
        "row": 3,
        "col": 1,
        "x": 224.0,
        "y": 272.0
      },
      "connections": [
        "node_13"
      ],
      "icon": "/assets/talents/UI/Textures/Common/Icon/Silhouette/Talent/64/Aura_64.webp"
    },
    {
      "id": "node_26",
      "name": "+18% 冰冷伤害",
      "type": "notable",
      "effects": [
        "+18% 冰冷伤害",
        "召唤物 +18% 冰冷伤害"
      ],
      "requiredPoints": 3,
      "maxPoints": 3,
      "currentPoints": 0,
      "position": {
        "row": 5,
        "col": 1,
        "x": 224.0,
        "y": 464.0
      },
      "connections": [
        "node_25"
      ],
      "icon": "/assets/talents/UI/Textures/Common/Icon/Silhouette/Talent/64/DmgAll_64.webp"
    },
    {
      "id": "node_7",
      "name": "+3% 攻击与施法速度",
      "type": "small",
      "effects": [
        "+3% 攻击与施法速度",
        "+3% 召唤物攻击与施法速度"
      ],
      "requiredPoints": 3,
      "maxPoints": 3,
      "currentPoints": 0,
      "position": {
        "row": 2,
        "col": 1,
        "x": 224.0,
        "y": 176.0
      },
      "connections": [
        "node_8"
      ],
      "icon": "/assets/talents/UI/Textures/Common/Icon/Silhouette/Talent/64/Atk_64.webp"
    },
    {
      "id": "node_19",
      "name": "+4% 最大魔力",
      "type": "small",
      "effects": [
        "+4% 最大魔力"
      ],
      "requiredPoints": 3,
      "maxPoints": 3,
      "currentPoints": 0,
      "position": {
        "row": 4,
        "col": 1,
        "x": 224.0,
        "y": 368.0
      },
      "connections": [
        "node_20"
      ],
      "icon": "/assets/talents/UI/Textures/Common/Icon/Silhouette/Talent/64/Dagger02_64.webp"
    },
    {
      "id": "node_8",
      "name": "+6% 攻击与施法速度",
      "type": "notable",
      "effects": [
        "+6% 攻击与施法速度",
        "+6% 召唤物攻击与施法速度"
      ],
      "requiredPoints": 6,
      "maxPoints": 3,
      "currentPoints": 0,
      "position": {
        "row": 2,
        "col": 2,
        "x": 352.0,
        "y": 176.0
      },
      "connections": [
        "node_7",
        "node_9"
      ],
      "icon": "/assets/talents/UI/Textures/Common/Icon/Silhouette/Talent/64/Atk_64.webp"
    },
    {
      "id": "node_20",
      "name": "+8% 最大魔力",
      "type": "notable",
      "effects": [
        "+8% 最大魔力"
      ],
      "requiredPoints": 6,
      "maxPoints": 3,
      "currentPoints": 0,
      "position": {
        "row": 4,
        "col": 2,
        "x": 352.0,
        "y": 368.0
      },
      "connections": [
        "node_19"
      ],
      "icon": "/assets/talents/UI/Textures/Common/Icon/Silhouette/Talent/64/Freeze_64.webp"
    },
    {
      "id": "node_2",
      "name": "+15% 暴击值",
      "type": "small",
      "effects": [
        "+15% 暴击值",
        "+15% 召唤物暴击值"
      ],
      "requiredPoints": 6,
      "maxPoints": 3,
      "currentPoints": 0,
      "position": {
        "row": 1,
        "col": 2,
        "x": 352.0,
        "y": 80.0
      },
      "connections": [
        "node_3"
      ],
      "icon": "/assets/talents/UI/Textures/Common/Icon/Silhouette/Talent/64/Crit01_64.webp"
    },
    {
      "id": "node_15",
      "name": "+4% 冰冷抗性",
      "type": "small",
      "effects": [
        "+4% 冰冷抗性"
      ],
      "requiredPoints": 6,
      "maxPoints": 3,
      "currentPoints": 0,
      "position": {
        "row": 3,
        "col": 2,
        "x": 352.0,
        "y": 272.0
      },
      "connections": [
        "node_16"
      ],
      "icon": "/assets/talents/UI/Textures/Common/Icon/Silhouette/Talent/64/Dual03_64.webp"
    },
    {
      "id": "node_9",
      "name": "造成击中冰冷伤害时，施加冰结",
      "type": "legendary",
      "effects": [
        "造成击中冰冷伤害时，施加冰结"
      ],
      "requiredPoints": 9,
      "maxPoints": 1,
      "currentPoints": 0,
      "position": {
        "row": 2,
        "col": 3,
        "x": 480.0,
        "y": 176.0
      },
      "connections": [
        "node_8"
      ],
      "icon": "/assets/talents/UI/Textures/Common/Icon/Silhouette/Talent/64/DmgExtra_64.webp"
    },
    {
      "id": "node_16",
      "name": "+18% 冰冷抗性",
      "type": "legendary",
      "effects": [
        "+18% 冰冷抗性",
        "召唤物免疫冰冷伤害",
        "召唤物免疫冰结和冰封"
      ],
      "requiredPoints": 9,
      "maxPoints": 1,
      "currentPoints": 0,
      "position": {
        "row": 3,
        "col": 3,
        "x": 480.0,
        "y": 272.0
      },
      "connections": [
        "node_15"
      ],
      "icon": "/assets/talents/UI/Textures/Common/Icon/Silhouette/Talent/64/DmgCold_64.webp"
    },
    {
      "id": "node_3",
      "name": "+20% 暴击值",
      "type": "notable",
      "effects": [
        "+20% 暴击值",
        "+20% 召唤物暴击值",
        "+5% 暴击伤害",
        "+5% 召唤物暴击伤害"
      ],
      "requiredPoints": 9,
      "maxPoints": 3,
      "currentPoints": 0,
      "position": {
        "row": 1,
        "col": 3,
        "x": 480.0,
        "y": 80.0
      },
      "connections": [
        "node_2"
      ],
      "icon": "/assets/talents/UI/Textures/Common/Icon/Silhouette/Talent/64/Crit04_64.webp"
    },
    {
      "id": "node_21",
      "name": "1.5% 生命返还",
      "type": "small",
      "effects": [
        "1.5% 生命返还",
        "1.5% 护盾返还"
      ],
      "requiredPoints": 9,
      "maxPoints": 3,
      "currentPoints": 0,
      "position": {
        "row": 4,
        "col": 3,
        "x": 480.0,
        "y": 368.0
      },
      "connections": [
        "node_22"
      ],
      "icon": "/assets/talents/UI/Textures/Common/Icon/Silhouette/Talent/64/Defence02_64.webp"
    },
    {
      "id": "node_27",
      "name": "1.5% 冰冷穿透",
      "type": "small",
      "effects": [
        "1.5% 冰冷穿透",
        "召唤物 1.5% 冰冷穿透"
      ],
      "requiredPoints": 9,
      "maxPoints": 3,
      "currentPoints": 0,
      "position": {
        "row": 5,
        "col": 3,
        "x": 480.0,
        "y": 464.0
      },
      "connections": [
        "node_28"
      ],
      "icon": "/assets/talents/UI/Textures/Common/Icon/Silhouette/Talent/64/Es_64.webp"
    },
    {
      "id": "node_28",
      "name": "对冰封敌人造成伤害时，施加 冰冷渗透",
      "type": "legendary",
      "effects": [
        "对冰封敌人造成伤害时，施加 冰冷渗透"
      ],
      "requiredPoints": 12,
      "maxPoints": 1,
      "currentPoints": 0,
      "position": {
        "row": 5,
        "col": 4,
        "x": 608.0,
        "y": 464.0
      },
      "connections": [
        "node_27"
      ],
      "icon": "/assets/talents/UI/Textures/Common/Icon/Silhouette/Talent/64/DmgEle_64.webp"
    },
    {
      "id": "node_22",
      "name": "+3% 生命返还",
      "type": "notable",
      "effects": [
        "+3% 生命返还",
        "+3% 护盾返还"
      ],
      "requiredPoints": 12,
      "maxPoints": 3,
      "currentPoints": 0,
      "position": {
        "row": 4,
        "col": 4,
        "x": 608.0,
        "y": 368.0
      },
      "connections": [
        "node_21"
      ],
      "icon": "/assets/talents/UI/Textures/Common/Icon/Silhouette/Talent/64/Defence02_64.webp"
    },
    {
      "id": "node_4",
      "name": "+2 冰结值上限",
      "type": "small",
      "effects": [
        "+2 冰结值上限"
      ],
      "requiredPoints": 12,
      "maxPoints": 3,
      "currentPoints": 0,
      "position": {
        "row": 1,
        "col": 4,
        "x": 608.0,
        "y": 80.0
      },
      "connections": [
        "node_5"
      ],
      "icon": "/assets/talents/UI/Textures/Common/Icon/Silhouette/Talent/64/Bow02_64.webp"
    },
    {
      "id": "node_10",
      "name": "对冰结的敌人，+20% 暴击值",
      "type": "small",
      "effects": [
        "对冰结的敌人，+20% 暴击值"
      ],
      "requiredPoints": 12,
      "maxPoints": 3,
      "currentPoints": 0,
      "position": {
        "row": 2,
        "col": 4,
        "x": 608.0,
        "y": 176.0
      },
      "connections": [
        "node_11"
      ],
      "icon": "/assets/talents/UI/Textures/Common/Icon/Silhouette/Talent/64/DmgExtra_64.webp"
    },
    {
      "id": "node_17",
      "name": "+8 智慧",
      "type": "small",
      "effects": [
        "+8 智慧"
      ],
      "requiredPoints": 12,
      "maxPoints": 3,
      "currentPoints": 0,
      "position": {
        "row": 3,
        "col": 4,
        "x": 608.0,
        "y": 272.0
      },
      "connections": [
        "node_18"
      ],
      "icon": "/assets/talents/UI/Textures/Common/Icon/Silhouette/Talent/64/Blind_64.webp"
    },
    {
      "id": "node_5",
      "name": "+5 冰结值上限",
      "type": "notable",
      "effects": [
        "+5 冰结值上限"
      ],
      "requiredPoints": 15,
      "maxPoints": 3,
      "currentPoints": 0,
      "position": {
        "row": 1,
        "col": 5,
        "x": 736.0,
        "y": 80.0
      },
      "connections": [
        "node_4",
        "node_6"
      ],
      "icon": "/assets/talents/UI/Textures/Common/Icon/Silhouette/Talent/64/Bow02_64.webp"
    },
    {
      "id": "node_11",
      "name": "对冰结的敌人，+20% 暴击伤害",
      "type": "notable",
      "effects": [
        "对冰结的敌人，+20% 暴击伤害"
      ],
      "requiredPoints": 15,
      "maxPoints": 3,
      "currentPoints": 0,
      "position": {
        "row": 2,
        "col": 5,
        "x": 736.0,
        "y": 176.0
      },
      "connections": [
        "node_10",
        "node_12"
      ],
      "icon": "/assets/talents/UI/Textures/Common/Icon/Silhouette/Talent/64/DmgExtra_64.webp"
    },
    {
      "id": "node_18",
      "name": "+5% 智慧",
      "type": "notable",
      "effects": [
        "+5% 智慧"
      ],
      "requiredPoints": 15,
      "maxPoints": 3,
      "currentPoints": 0,
      "position": {
        "row": 3,
        "col": 5,
        "x": 736.0,
        "y": 272.0
      },
      "connections": [
        "node_17"
      ],
      "icon": "/assets/talents/UI/Textures/Common/Icon/Silhouette/Talent/64/Flask02_64.webp"
    },
    {
      "id": "node_23",
      "name": "+10% 聚能祝福持续时间",
      "type": "small",
      "effects": [
        "+10% 聚能祝福持续时间",
        "拥有聚能祝福时， +10% 伤害"
      ],
      "requiredPoints": 15,
      "maxPoints": 3,
      "currentPoints": 0,
      "position": {
        "row": 4,
        "col": 5,
        "x": 736.0,
        "y": 368.0
      },
      "connections": [
        "node_24"
      ],
      "icon": "/assets/talents/UI/Textures/Common/Icon/Silhouette/Talent/64/Crit01_64.webp"
    },
    {
      "id": "node_29",
      "name": "+9% 冰冷伤害",
      "type": "small",
      "effects": [
        "+9% 冰冷伤害",
        "召唤物 +9% 冰冷伤害"
      ],
      "requiredPoints": 15,
      "maxPoints": 3,
      "currentPoints": 0,
      "position": {
        "row": 5,
        "col": 5,
        "x": 736.0,
        "y": 464.0
      },
      "connections": [
        "node_30"
      ],
      "icon": "/assets/talents/UI/Textures/Common/Icon/Silhouette/Talent/64/DmgCold_64.webp"
    },
    {
      "id": "node_6",
      "name": "对冰封的敌人额外 +10% 伤害",
      "type": "legendary",
      "effects": [
        "对冰封的敌人额外 +10% 伤害"
      ],
      "requiredPoints": 18,
      "maxPoints": 1,
      "currentPoints": 0,
      "position": {
        "row": 1,
        "col": 6,
        "x": 864.0,
        "y": 80.0
      },
      "connections": [
        "node_5"
      ],
      "icon": "/assets/talents/UI/Textures/Common/Icon/Silhouette/Talent/64/Bow02_64.webp"
    },
    {
      "id": "node_12",
      "name": "对冰结的敌人，+100 暴击值",
      "type": "legendary",
      "effects": [
        "对冰结的敌人，+100 暴击值"
      ],
      "requiredPoints": 18,
      "maxPoints": 1,
      "currentPoints": 0,
      "position": {
        "row": 2,
        "col": 6,
        "x": 864.0,
        "y": 176.0
      },
      "connections": [
        "node_11"
      ],
      "icon": "/assets/talents/UI/Textures/Common/Icon/Silhouette/Talent/64/DmgCold_64.webp"
    },
    {
      "id": "node_24",
      "name": "对冰结敌人造成伤害时，+100% 几率获得 1 层聚能祝福，间隔 0.1 秒",
      "type": "legendary",
      "effects": [
        "对冰结敌人造成伤害时，+100% 几率获得 1 层聚能祝福，间隔 0.1 秒"
      ],
      "requiredPoints": 18,
      "maxPoints": 1,
      "currentPoints": 0,
      "position": {
        "row": 4,
        "col": 6,
        "x": 864.0,
        "y": 368.0
      },
      "connections": [
        "node_23"
      ],
      "icon": "/assets/talents/UI/Textures/Common/Icon/Silhouette/Talent/64/Ailment_64.webp"
    },
    {
      "id": "node_30",
      "name": "100% 物理伤害转化为冰冷伤害",
      "type": "legendary",
      "effects": [
        "100% 物理伤害转化为冰冷伤害",
        "召唤物 100% 物理伤害转化为冰冷伤害"
      ],
      "requiredPoints": 18,
      "maxPoints": 1,
      "currentPoints": 0,
      "position": {
        "row": 5,
        "col": 6,
        "x": 864.0,
        "y": 464.0
      },
      "connections": [
        "node_29"
      ],
      "icon": "/assets/talents/UI/Textures/Common/Icon/Silhouette/Talent/64/DmgExtra_64.webp"
    }
  ],
  "isGodRoot": false
}
